{
  "deploy": {
    "mode": "blue-green",
    "activeSlot": "blue",
    "lastCommit": "8abbcaf829ad4a6c6deb5a1d62053767037488ec",
    "updatedAt": "2026-03-20T23:48:26.714Z",
    "upstreamConf": "/etc/nginx/snippets/velvetdinosaur-active-upstream.conf",
    "activeLink": "/srv/apps/velvetdinosaur-current",
    "slots": {
      "blue": {
        "path": "/srv/apps/velvetdinosaur-blue",
        "port": 3018,
        "service": "vd-velvetdinosaur-blue",
        "envFile": "/srv/apps/velvetdinosaur-blue/.env.production"
      },
      "green": {
        "path": "/srv/apps/velvetdinosaur-green",
        "port": 3019,
        "service": "vd-velvetdinosaur-green",
        "envFile": "/srv/apps/velvetdinosaur-green/.env.production"
      }
    }
  }
}
